checkpointed_core/__init__.py
checkpointed_core/checkpointing.py
checkpointed_core/data_format.py
checkpointed_core/data_store.py
checkpointed_core/executor.py
checkpointed_core/graph.py
checkpointed_core/handle.py
checkpointed_core/instructions.py
checkpointed_core/lazy_file.py
checkpointed_core/pipeline.py
checkpointed_core/plan.py
checkpointed_core/step.py
checkpointed_core/parameters/__init__.py
checkpointed_core/parameters/arguments.py
checkpointed_core/parameters/constraints.py
checkpointed_core/parameters/core.py
checkpointed_core/parameters/errors.py
checkpointed_core/parameters/parsing.py
checkpointed_core/parameters/schemas.py
checkpointed_core-1.0.0.dist-info/LICENSE
checkpointed_core-1.0.0.dist-info/METADATA
checkpointed_core-1.0.0.dist-info/WHEEL
checkpointed_core-1.0.0.dist-info/top_level.txt
checkpointed_core-1.0.0.dist-info/RECORD
