Metadata-Version: 2.1
Name: checkpointed-core
Version: 1.0.0
Author-email: Jesse Maarleveld <jessemaarleveld@gmail.com>
Maintainer-email: Jesse Maarleveld <jessemaarleveld@gmail.com>
License: GNU GENERAL PUBLIC LICENSE
Requires-Python: >=3.10
License-File: LICENSE
